pymp/__init__.py
pymp/logging_utils.py
pymp/planner.py
pymp/robot.py
pymp/srdf_utils.py
pymp/utils.py
pymp/path_planning/__init__.py
pymp/path_planning/core.py
pymp/path_planning/rrt.py
pymp/path_planning/rrt_connect.py
motion_planning-0.1.5.dist-info/LICENSE
motion_planning-0.1.5.dist-info/METADATA
motion_planning-0.1.5.dist-info/WHEEL
motion_planning-0.1.5.dist-info/top_level.txt
motion_planning-0.1.5.dist-info/RECORD
