Metadata-Version: 2.1
Name: motion-planning
Version: 0.1.5
Summary: A pythonic motion planning library
Home-page: https://github.com/Jiayuan-Gu/pymp
Author: Jiayuan Gu
Author-email: jigu@ucsd.edu
Keywords: robotics motion-planning
Requires-Python: >=3.7
License-File: LICENSE
Requires-Dist: numpy
Requires-Dist: pin (>=2.6.13)
Requires-Dist: toppra (>=0.4.1)
Requires-Dist: lxml
Requires-Dist: beautifulsoup4
Requires-Dist: trimesh
Provides-Extra: meshcat
Requires-Dist: meshcat ; extra == 'meshcat'
Provides-Extra: tests
Requires-Dist: pytest ; extra == 'tests'
Requires-Dist: black ; extra == 'tests'
Requires-Dist: isort ; extra == 'tests'
